setup.py
mediatumtal/__init__.py
mediatumtal/tal.py
mediatumtal/talextracted.py
mediatumtal.egg-info/PKG-INFO
mediatumtal.egg-info/SOURCES.txt
mediatumtal.egg-info/dependency_links.txt
mediatumtal.egg-info/pbr.json
mediatumtal.egg-info/top_level.txt