Metadata-Version: 1.1
Name: mediatumtal
Version: 0.3.1
Summary: TAL template library used by mediaTUM extracted from Athana web server
Home-page: https://mediatumdev.ub.tum.de/projects/mediatum-tal
Author: Tobias Stenzel (original author: ?)
Author-email: tobias.stenzel@tum.de
License: GNU General Public License v3 (GPLv3)
Keywords: tal template mediatum
Platform: UNKNOWN
Classifier: Development Status :: 3 - Alpha
Classifier: Intended Audience :: Developers
Classifier: License :: OSI Approved :: GNU General Public License v3 (GPLv3)
Classifier: Programming Language :: Python :: 2
Classifier: Programming Language :: Python :: 2.7
